ms_adapter/__init__.py
ms_adapter/utils.py
ms_adapter/pytorch/__init__.py
ms_adapter/pytorch/_six.py
ms_adapter/pytorch/_utils.py
ms_adapter/pytorch/conflict_functional.py
ms_adapter/pytorch/functional.py
ms_adapter/pytorch/package_info.py
ms_adapter/pytorch/random.py
ms_adapter/pytorch/storage.py
ms_adapter/pytorch/tensor.py
ms_adapter/pytorch/_ref/__init__.py
ms_adapter/pytorch/_register/__init__.py
ms_adapter/pytorch/_register/getitem_impl.py
ms_adapter/pytorch/_register/register_multitype_ops.py
ms_adapter/pytorch/_register/register_standard_method.py
ms_adapter/pytorch/_register/register_utils.py
ms_adapter/pytorch/autograd/__init__.py
ms_adapter/pytorch/autograd/function.py
ms_adapter/pytorch/autograd/variable.py
ms_adapter/pytorch/common/__init__.py
ms_adapter/pytorch/common/_inner.py
ms_adapter/pytorch/common/device.py
ms_adapter/pytorch/common/dtype.py
ms_adapter/pytorch/cuda/__init__.py
ms_adapter/pytorch/fft/__init__.py
ms_adapter/pytorch/fft/fft.py
ms_adapter/pytorch/nn/__init__.py
ms_adapter/pytorch/nn/functional.py
ms_adapter/pytorch/nn/init.py
ms_adapter/pytorch/nn/parameter.py
ms_adapter/pytorch/nn/modules/__init__.py
ms_adapter/pytorch/nn/modules/activation.py
ms_adapter/pytorch/nn/modules/batchnorm.py
ms_adapter/pytorch/nn/modules/container.py
ms_adapter/pytorch/nn/modules/conv.py
ms_adapter/pytorch/nn/modules/distance.py
ms_adapter/pytorch/nn/modules/dropout.py
ms_adapter/pytorch/nn/modules/flatten.py
ms_adapter/pytorch/nn/modules/linear.py
ms_adapter/pytorch/nn/modules/loss.py
ms_adapter/pytorch/nn/modules/module.py
ms_adapter/pytorch/nn/modules/normalization.py
ms_adapter/pytorch/nn/modules/padding.py
ms_adapter/pytorch/nn/modules/pooling.py
ms_adapter/pytorch/nn/modules/rnn.py
ms_adapter/pytorch/nn/modules/sparse.py
ms_adapter/pytorch/nn/modules/unpooling.py
ms_adapter/pytorch/nn/modules/upsampling.py
ms_adapter/pytorch/nn/modules/utils.py
ms_adapter/pytorch/optim/__init__.py
ms_adapter/pytorch/utils/__init__.py
ms_adapter-0.1.0.dist-info/LICENSE
ms_adapter-0.1.0.dist-info/METADATA
ms_adapter-0.1.0.dist-info/WHEEL
ms_adapter-0.1.0.dist-info/top_level.txt
ms_adapter-0.1.0.dist-info/RECORD
